pappardelle/__init__.py
pappardelle/date_helpers.py
pappardelle/dict_helpers.py
pappardelle/function_helpers.py
pappardelle/lists_helpers.py
pappardelle/string_helpers.py
pappardelle/value_helpers.py
pappardelle-0.16.dist-info/LICENSE
pappardelle-0.16.dist-info/METADATA
pappardelle-0.16.dist-info/WHEEL
pappardelle-0.16.dist-info/top_level.txt
pappardelle-0.16.dist-info/RECORD
