Metadata-Version: 2.1
Name: pappardelle
Version: 0.16
Summary: UNKNOWN
Home-page: UNKNOWN
License: UNKNOWN
Platform: UNKNOWN
License-File: LICENSE
